[
    {
        "name": "kyworn-github-io",
        "description": "Personal GitHub Portfolio Website",
        "html_url": "https://github.com/Kyworn/kyworn.github.io",
        "homepage": "https://kyworn.github.io",
        "readmeTitle": "Personal Portfolio Website"
    },
    {
        "name": "taptracker",
        "description": "Web application to measure and analyze input performance with precision, tracking click speed and keyboard input characteristics",
        "html_url": "https://github.com/Kyworn/taptracker",
        "homepage": "https://kyworn.github.io/taptracker",
        "readmeTitle": "Input Performance Analyzer for Clicks and Keystrokes"
    }
]